target_avro/__init__.py
target_avro/converter.py
target_avro-0.2.0.dist-info/entry_points.txt
target_avro-0.2.0.dist-info/WHEEL
target_avro-0.2.0.dist-info/METADATA
target_avro-0.2.0.dist-info/RECORD
