Metadata-Version: 2.1
Name: target-avro
Version: 0.2.0
Summary: Singer.io target for extracting data
Home-page: https://github.com/kageboushi-app/target-avro
License: AGPL-3.0
Author: inamura
Author-email: inamura@kageboushi.app
Requires-Python: >=3.8,<4.0
Classifier: License :: OSI Approved :: GNU Affero General Public License v3
Classifier: Programming Language :: Python :: 3
Classifier: Programming Language :: Python :: 3.8
Classifier: Programming Language :: Python :: 3.9
Requires-Dist: fastavro (>=1.3.4,<2.0.0)
Requires-Dist: singer-python (>=5,<6)
Requires-Dist: smart_open (>=5.0.0,<6.0.0)
Requires-Dist: strict_rfc3339 (>=0.7,<0.8)
Project-URL: Repository, https://github.com/kageboushi-app/target-avro
